setup.py
Akamu.egg-info/PKG-INFO
Akamu.egg-info/SOURCES.txt
Akamu.egg-info/dependency_links.txt
Akamu.egg-info/not-zip-safe
Akamu.egg-info/requires.txt
Akamu.egg-info/top_level.txt
lib/__init__.py
lib/config/__init__.py
lib/config/dataset.py
lib/config/diglot.py
lib/demo/__init__.py
lib/demo/gsp.py
lib/demo/gsp_validator.py
lib/demo/musicbrainz.py
lib/demo/protocol.py
lib/demo/web_acl.py
lib/demo/wheezy.py
lib/demo/xslt.py
lib/diglot/__init__.py
lib/protocol/grddlstore.py
lib/protocol/sparql.py
lib/security/__init__.py
lib/security/acl.py
lib/security/repoze.py
lib/util/__init__.py
lib/wheezy/__init__.py
lib/xslt/__init__.py
lib/xslt/extensions.py
test/test_diglot.py
test/test_web_acl.py
test/test_wheezy.py
test/test_xslt.py