Metadata-Version: 1.0
Name: Akamu
Version: 0.7
Summary: An Akara module for managing the use of an RDF dataset, a XML/RDF filesystem, and XSLT extension functions within a web application
Home-page: UNKNOWN
Author: UNKNOWN
Author-email: UNKNOWN
License: UNKNOWN
Platform: UNKNOWN
